pandoc_pyrun/__init__.py
pandoc_pyrun/pandoc_pyrun.py
pandoc_pyrun-1.0.2.dist-info/LICENSE
pandoc_pyrun-1.0.2.dist-info/METADATA
pandoc_pyrun-1.0.2.dist-info/WHEEL
pandoc_pyrun-1.0.2.dist-info/entry_points.txt
pandoc_pyrun-1.0.2.dist-info/top_level.txt
pandoc_pyrun-1.0.2.dist-info/RECORD
