Metadata-Version: 2.1
Name: pandoc-pyrun
Version: 1.0.2
Summary: Pandoc filter to run python code blocks
Home-page: https://gitlab-fil.univ-lille.fr/phm/pandoc-pyrun
Author: D'hulst Thomas, Tayebi Ajwad
Author-email: thomas.dhulst@hotmail.fr, ajwad.tayebi@gmail.com
License: BDS2
Download-URL: https://gitlab-fil.univ-lille.fr/phm/pandoc-pyrun/-/archive/master/pandoc-pyrun-master.tar.gz
Keywords: pandoc filters markdown python notes pandocfilters pdf latex
Platform: UNKNOWN
Classifier: Development Status :: 3 - Alpha
Classifier: Topic :: Utilities
Classifier: License :: OSI Approved :: BSD License
Classifier: Programming Language :: Python :: 3.4
Classifier: Programming Language :: Python :: 3.5
Classifier: Programming Language :: Python :: 3.6
Classifier: Environment :: Console
Classifier: Intended Audience :: End Users/Desktop
Classifier: Intended Audience :: Developers
Classifier: Topic :: Software Development :: Build Tools
Classifier: Topic :: Software Development :: Documentation
Classifier: Topic :: Text Processing :: Filters
Requires-Python: >=3.6,<4
License-File: LICENSE
Requires-Dist: pandocfilters
Requires-Dist: matplotlib
Provides-Extra: dev
Requires-Dist: check-manifest ; extra == 'dev'
Provides-Extra: test
Requires-Dist: coverage ; extra == 'test'
